Metadata-Version: 1.0
Name: dash-toggle
Version: 0.0.3
Summary: A toggle component wrapper to be used in dash projects
Home-page: UNKNOWN
Author: Zeke Ayonrinde zeke.ayonrinde@15gifts.com
Author-email: UNKNOWN
License: MIT
Platform: UNKNOWN
